Metadata-Version: 2.1
Name: jgbpacking
Version: 0.0.3
Summary: PACKAGE MODELO CLASIFICACION WINE
Requires-Python: >=3.6.0
Requires-Dist: numpy (==1.23.0)
Requires-Dist: pandas (<1.4.0,>=1.3.5)
Requires-Dist: pydantic (<1.9.0,>=1.8.1)
Requires-Dist: scikit-learn (<1.1.0,>=1.0.2)
Requires-Dist: strictyaml (<1.4.0,>=1.3.2)
Requires-Dist: ruamel.yaml (==0.16.12)
Requires-Dist: feature-engine (<1.1.0,>=1.0.2)
Requires-Dist: joblib (<1.1.0,>=1.0.1)
Requires-Dist: pyspark (==3.4.0)
